{"version":"0.4","title":"Level 1 Step 1","type":"section","content":[{"id":"6f81d1cd","settings":{"margin":{"unit":"px","top":"0","right":0,"bottom":"20","left":0,"isLinked":false},"border_border":"solid","border_width":{"unit":"px","top":"0","right":"0","bottom":"1","left":"0","isLinked":false},"border_color":"#cccccc","padding":{"unit":"px","top":"20","right":"0","bottom":"20","left":"0","isLinked":false}},"elements":[{"id":"4ef721b1","settings":{"_column_size":100},"elements":[{"id":"ae7dbbf","settings":{"title":"Step 1<span style=\"font-size: 1.625rem;\"><\/span><br>","title_color":"#2a282b"},"elements":[],"isInner":false,"widgetType":"heading","elType":"widget"},{"id":"3d136f74","settings":{"title":"Objective:","header_size":"h4"},"elements":[],"isInner":false,"widgetType":"heading","elType":"widget"},{"id":"4e4a84d7","settings":{"editor":"<p>Learn about the HTML &lt;section&gt; tag, and CSS classes. There's actually nothing visible at this point, we'll start adding content in the next step!<\/p>"},"elements":[],"isInner":false,"widgetType":"text-editor","elType":"widget"},{"id":"575959e5","settings":{"tabs":[{"tab_title":"Instructions","tab_content":"<p>Create a &lt;section&gt; element to contain your profile content, and give it a sensible class name for future use<\/p>","_id":"1e695b6"},{"tab_title":"Outline Code","tab_content":"<pre class=\"EnlighterJSRAW\" data-enlighter-language=\"html\">\n<section class=\"\">\n\n<\/section>\n<\/pre>","_id":"5ef6d0d"},{"tab_title":"Example Code","tab_content":"<pre class=\"EnlighterJSRAW\" data-enlighter-language=\"html\">\n<section class=\"profile-bio\">\n\n<\/section>\n<\/pre>","_id":"19e7214"}]},"elements":[],"isInner":false,"widgetType":"tabs","elType":"widget"},{"id":"7e1fb8bc","settings":{"title":"Example Screenshot:","header_size":"h4","_margin":{"unit":"px","top":"0","right":"0","bottom":"0","left":"0","isLinked":true},"_padding":{"unit":"px","top":"0","right":"0","bottom":"0","left":"0","isLinked":true}},"elements":[],"isInner":false,"widgetType":"heading","elType":"widget"},{"id":"5985b16d","settings":{"image":{"url":"https:\/\/edincoder.tk\/wp-content\/uploads\/2018\/01\/level-1-step-1.png","id":189},"image_size":"medium","align":"left","link_to":"file","open_lightbox":"yes","image_box_shadow_box_shadow_type":"yes"},"elements":[],"isInner":false,"widgetType":"image","elType":"widget"}],"isInner":false,"elType":"column"}],"isInner":false,"elType":"section"}]}